Metadata-Version: 2.1
Name: akramcul
Version: 0.0
Summary: Just for fun, doesn't contains any useful function
Author-email: akramMohamed123@gamil.com
